{
  "date": "2026-04-09",
  "source": "https://www.shmeea.edu.cn/page/03000/",
  "items": [
    {"title": "转载：上海市教育委员会关于做好2026年上海市高中阶段学校招收...", "url": "https://edu.sh.gov.cn/xxgk2_zdgz_rxgkyzs_03/20260331/00af813278714810959cbc4069f86f01.html", "date": "2026-03-31", "tags": ["2026", "高中招生"]},
    {"title": "转载：上海市教育委员会关于做好2026年上海市中等职业学校自主...", "url": "https://edu.sh.gov.cn/xxgk2_zdgz_zyjy_03/20260325/4b275ac9af5f488da02ca525a45cbe59.html", "date": "2026-03-25", "tags": ["2026", "中职自主"]},
    {"title": "转载：上海市教育委员会关于做好2026年上海市全日制普通中等职...", "url": "https://edu.sh.gov.cn/xxgk2_zdgz_rxgkyzs_03/20260325/bc14fe73790248a69ee507d71c26bbda.html", "date": "2026-03-25", "tags": ["2026", "中等职业"]},
    {"title": "转载：上海市教育委员会 上海市体育局关于做好2026年上海市高...", "url": "https://edu.sh.gov.cn/xxgk2_zdgz_rxgkyzs_03/20260318/77189879eaa4443a9554e13c000bd6cc.html", "date": "2026-03-18", "tags": ["2026", "体育特长"]},
    {"title": "2026年本市高中阶段学校招生网上报名及信息确认将于1月19日开始", "url": "https://www.shmeea.edu.cn/page/03300/20260112/20005.html", "date": "2026-01-12", "tags": ["2026", "报名"]},
    {"title": "关于《2026年上海中考中招指南（报名篇、考试篇、信息篇）》一...", "url": "https://www.shmeea.edu.cn/page/03300/20251229/19965.html", "date": "2025-12-29", "tags": ["2026", "指南"]}
  ],
  "pdf_links": [
    "https://www.shmeea.edu.cn/download/20250528/016.pdf"
  ]
}
